ESMCBA/ESMC_embeddings.py
ESMCBA/HLA_full_sequences_UMAP.py
ESMCBA/__init__.py
ESMCBA/cli.py
ESMCBA/embeddings_generation.py
ESMCBA/embeddings_generation_main.py
ESMCBA/evaluation_IEDB_qual.py
ESMCBA/forward_pass_unsupervised.py
ESMCBA/graph_utils.py
ESMCBA/imports.py
ESMCBA/make_ESMCBA_models.py
ESMCBA/model_evaluation.py
ESMCBA/other_utils.py
ESMCBA/registry.py
ESMCBA/run_RFDiffusionMHC_epitope.py
ESMCBA/models/ESM_Supervised/ESM-C_BA_09022025.py
ESMCBA/models/ESM_Supervised/ESM-C_BA_21032025.py
ESMCBA/models/ESM_Supervised/ESMCBA_classifier.py
ESMCBA/models/ESM_Unsupervised/ESM-C_ALLHLAs.py
esmcba-0.1.4.dist-info/licenses/LICENSE
esmcba-0.1.4.dist-info/METADATA
esmcba-0.1.4.dist-info/WHEEL
esmcba-0.1.4.dist-info/entry_points.txt
esmcba-0.1.4.dist-info/top_level.txt
esmcba-0.1.4.dist-info/RECORD
