Metadata-Version: 2.4
Name: esmcba
Version: 0.1.4
Summary: ESM-Cambrian Binding Affinity prediction for peptide-MHC binding
Author-email: Sergio Mares <sergiomar10@berkeley.edu>
License: MIT
Project-URL: Homepage, https://github.com/sermare/ESMCBA
Project-URL: Repository, https://github.com/sermare/ESMCBA
Project-URL: Models, https://huggingface.co/smares/ESMCBA
Project-URL: Documentation, https://github.com/sermare/ESMCBA#readme
Project-URL: Bug Reports, https://github.com/sermare/ESMCBA/issues
Keywords: protein,MHC,binding,ESM,transformers,immunology
Classifier: Development Status :: 3 - Alpha
Classifier: Intended Audience :: Science/Research
Classifier: Programming Language :: Python :: 3
Classifier: Programming Language :: Python :: 3.8
Classifier: Programming Language :: Python :: 3.9
Classifier: Programming Language :: Python :: 3.10
Classifier: Topic :: Scientific/Engineering :: Bio-Informatics
Requires-Python: >=3.8
License-File: LICENSE
Requires-Dist: torch>=2.0.0
Requires-Dist: transformers>=4.30.0
Requires-Dist: esm>=3.0.0
Requires-Dist: huggingface-hub<1.0,>=0.16.0
Requires-Dist: biopython>=1.79
Requires-Dist: umap-learn>=0.5.0
Requires-Dist: scikit-learn>=1.0.0
Requires-Dist: seaborn>=0.11.0
Requires-Dist: pandas>=1.3.0
Requires-Dist: matplotlib>=3.4.0
Requires-Dist: numpy>=1.20.0
Provides-Extra: dev
Requires-Dist: pytest>=7.0.0; extra == "dev"
Requires-Dist: black>=22.0.0; extra == "dev"
Requires-Dist: flake8>=4.0.0; extra == "dev"
Provides-Extra: transfer
Requires-Dist: hf_transfer>=0.1.0; extra == "transfer"
Dynamic: license-file
